{"NSE": {"NIFTY 50": {"SMA": {"sma50": "BUY_SIGNAL", "sma100": "BUY_SIGNAL", "sma200": "BUY_SIGNAL", "sma_signal": "BUY_SIGNAL"}, "token": "256265"}, "INFY": {"SMA": {"sma50": "", "sma100": "", "sma200": "", "sma_signal": ""}, "token": "408065"}, "YESBANK": {"SMA": {"sma50": "", "sma100": "", "sma200": "", "sma_signal": ""}, "token": "3050241"}, "INFRATEL": {"SMA": {"sma50": "", "sma100": "BUY_SIGNAL", "sma200": "SELL_SIGNAL", "sma_signal": ""}, "token": "7458561"}, "SUNPHARMA": {"SMA": {"sma50": "SELL_SIGNAL", "sma100": "", "sma200": "", "sma_signal": "SELL_SIGNAL"}, "token": "857857"}, "GRASIM": {"SMA": {"sma50": "BUY_SIGNAL", "sma100": "", "sma200": "", "sma_signal": "BUY_SIGNAL"}, "token": "315393"}, "DRREDDY": {"SMA": {"sma50": "BUY_SIGNAL", "sma100": "BUY_SIGNAL", "sma200": "", "sma_signal": "BUY_SIGNAL"}, "token": "225537"}, "HINDPETRO": {"SMA": {"sma50": "BUY_SIGNAL", "sma100": "BUY_SIGNAL", "sma200": "", "sma_signal": "BUY_SIGNAL"}, "token": "359937"}, "IOC": {"SMA": {"sma50": "SELL_SIGNAL", "sma100": "SELL_SIGNAL", "sma200": "", "sma_signal": "SELL_SIGNAL"}, "token": "415745"}, "HINDUNILVR": {"SMA": {"sma50": "BUY_SIGNAL", "sma100": "BUY_SIGNAL", "sma200": "", "sma_signal": "BUY_SIGNAL"}, "token": "356865"}, "HCLTECH": {"SMA": {"sma50": "SELL_SIGNAL", "sma100": "", "sma200": "SELL_SIGNAL", "sma_signal": "SELL_SIGNAL"}, "token": "1850625"}, "ZEEL": {"SMA": {"sma50": "SELL_SIGNAL", "sma100": "SELL_SIGNAL", "sma200": "", "sma_signal": "SELL_SIGNAL"}, "token": "975873"}, "BAJFINANCE": {"SMA": {"sma50": "BUY_SIGNAL", "sma100": "BUY_SIGNAL", "sma200": "", "sma_signal": "BUY_SIGNAL"}, "token": "81153"}, "ULTRACEMCO": {"SMA": {"sma50": "SELL_SIGNAL", "sma100": "SELL_SIGNAL", "sma200": "SELL_SIGNAL", "sma_signal": "SELL_SIGNAL"}, "token": "2952193"}, "UPL": {"SMA": {"sma50": "BUY_SIGNAL", "sma100": "", "sma200": "", "sma_signal": "BUY_SIGNAL"}, "token": "2889473"}, "ASIANPAINT": {"SMA": {"sma50": "BUY_SIGNAL", "sma100": "", "sma200": "", "sma_signal": "BUY_SIGNAL"}, "token": "60417"}, "KOTAKBANK": {"SMA": {"sma50": "SELL_SIGNAL", "sma100": "BUY_SIGNAL", "sma200": "SELL_SIGNAL", "sma_signal": ""}, "token": "492033"}, "EICHERMOT": {"SMA": {"sma50": "", "sma100": "", "sma200": "", "sma_signal": ""}, "token": "232961"}, "MARUTI": {"SMA": {"sma50": "SELL_SIGNAL", "sma100": "SELL_SIGNAL", "sma200": "", "sma_signal": "SELL_SIGNAL"}, "token": "2815745"}, "HDFCBANK": {"SMA": {"sma50": "BUY_SIGNAL", "sma100": "BUY_SIGNAL", "sma200": "BUY_SIGNAL", "sma_signal": "BUY_SIGNAL"}, "token": "341249"}, "HINDALCO": {"SMA": {"sma50": "", "sma100": "", "sma200": "", "sma_signal": ""}, "token": "348929"}, "ONGC": {"SMA": {"sma50": "SELL_SIGNAL", "sma100": "", "sma200": "", "sma_signal": "SELL_SIGNAL"}, "token": "633601"}, "ADANIPORTS": {"SMA": {"sma50": "", "sma100": "", "sma200": "", "sma_signal": ""}, "token": "3861249"}, "POWERGRID": {"SMA": {"sma50": "BUY_SIGNAL", "sma100": "BUY_SIGNAL", "sma200": "BUY_SIGNAL", "sma_signal": "BUY_SIGNAL"}, "token": "3834113"}, "CIPLA": {"SMA": {"sma50": "SELL_SIGNAL", "sma100": "", "sma200": "", "sma_signal": "SELL_SIGNAL"}, "token": "177665"}, "HEROMOTOCO": {"SMA": {"sma50": "SELL_SIGNAL", "sma100": "SELL_SIGNAL", "sma200": "", "sma_signal": "SELL_SIGNAL"}, "token": "345089"}, "SBIN": {"SMA": {"sma50": "BUY_SIGNAL", "sma100": "", "sma200": "", "sma_signal": "BUY_SIGNAL"}, "token": "779521"}, "COALINDIA": {"SMA": {"sma50": "", "sma100": "", "sma200": "", "sma_signal": ""}, "token": "5215745"}, "BPCL": {"SMA": {"sma50": "BUY_SIGNAL", "sma100": "", "sma200": "SELL_SIGNAL", "sma_signal": ""}, "token": "134657"}, "RELIANCE": {"SMA": {"sma50": "BUY_SIGNAL", "sma100": "SELL_SIGNAL", "sma200": "", "sma_signal": ""}, "token": "738561"}, "TITAN": {"SMA": {"sma50": "BUY_SIGNAL", "sma100": "", "sma200": "", "sma_signal": "BUY_SIGNAL"}, "token": "897537"}, "M&M": {"SMA": {"sma50": "SELL_SIGNAL", "sma100": "", "sma200": "", "sma_signal": "SELL_SIGNAL"}, "token": "519937"}, "ICICIBANK": {"SMA": {"sma50": "BUY_SIGNAL", "sma100": "", "sma200": "", "sma_signal": "BUY_SIGNAL"}, "token": "1270529"}, "ITC": {"SMA": {"sma50": "BUY_SIGNAL", "sma100": "BUY_SIGNAL", "sma200": "BUY_SIGNAL", "sma_signal": "BUY_SIGNAL"}, "token": "424961"}, "IBULHSGFIN": {"SMA": {"sma50": "", "sma100": "", "sma200": "", "sma_signal": ""}, "token": "7712001"}, "TATAMOTORS": {"SMA": {"sma50": "", "sma100": "", "sma200": "", "sma_signal": ""}, "token": "884737"}, "BAJAJ-AUTO": {"SMA": {"sma50": "SELL_SIGNAL", "sma100": "BUY_SIGNAL", "sma200": "SELL_SIGNAL", "sma_signal": ""}, "token": "4267265"}, "BAJAJFINSV": {"SMA": {"sma50": "", "sma100": "", "sma200": "", "sma_signal": ""}, "token": "4268801"}, "VEDL": {"SMA": {"sma50": "SELL_SIGNAL", "sma100": "", "sma200": "", "sma_signal": "SELL_SIGNAL"}, "token": "784129"}, "TATASTEEL": {"SMA": {"sma50": "", "sma100": "", "sma200": "", "sma_signal": ""}, "token": "895745"}, "TECHM": {"SMA": {"sma50": "BUY_SIGNAL", "sma100": "SELL_SIGNAL", "sma200": "BUY_SIGNAL", "sma_signal": ""}, "token": "3465729"}, "NTPC": {"SMA": {"sma50": "SELL_SIGNAL", "sma100": "", "sma200": "", "sma_signal": "SELL_SIGNAL"}, "token": "2977281"}, "WIPRO": {"SMA": {"sma50": "BUY_SIGNAL", "sma100": "BUY_SIGNAL", "sma200": "", "sma_signal": "BUY_SIGNAL"}, "token": "969473"}, "TCS": {"SMA": {"sma50": "SELL_SIGNAL", "sma100": "SELL_SIGNAL", "sma200": "BUY_SIGNAL", "sma_signal": ""}, "token": "2953217"}, "INDUSINDBK": {"SMA": {"sma50": "SELL_SIGNAL", "sma100": "", "sma200": "", "sma_signal": "SELL_SIGNAL"}, "token": "1346049"}, "HDFC": {"SMA": {"sma50": "BUY_SIGNAL", "sma100": "", "sma200": "", "sma_signal": "BUY_SIGNAL"}, "token": "340481"}, "JSWSTEEL": {"SMA": {"sma50": "", "sma100": "", "sma200": "", "sma_signal": ""}, "token": "3001089"}, "GAIL": {"SMA": {"sma50": "", "sma100": "", "sma200": "", "sma_signal": ""}, "token": "1207553"}, "BHARTIARTL": {"SMA": {"sma50": "", "sma100": "BUY_SIGNAL", "sma200": "", "sma_signal": "BUY_SIGNAL"}, "token": "2714625"}, "LT": {"SMA": {"sma50": "SELL_SIGNAL", "sma100": "SELL_SIGNAL", "sma200": "BUY_SIGNAL", "sma_signal": ""}, "token": "2939649"}, "AXISBANK": {"SMA": {"sma50": "", "sma100": "", "sma200": "", "sma_signal": ""}, "token": "1510401"}}}